cmem/__init__.py
cmem/cmempy/__init__.py
cmem/cmempy/api.py
cmem/cmempy/config.py
cmem/cmempy/custom_tasks/__init__.py
cmem/cmempy/dp/__init__.py
cmem/cmempy/dp/admin/__init__.py
cmem/cmempy/dp/admin/backup.py
cmem/cmempy/dp/authorization/__init__.py
cmem/cmempy/dp/authorization/conditions.py
cmem/cmempy/dp/authorization/refresh.py
cmem/cmempy/dp/proxy/__init__.py
cmem/cmempy/dp/proxy/graph.py
cmem/cmempy/dp/proxy/sparql.py
cmem/cmempy/dp/proxy/update.py
cmem/cmempy/dp/shacl/__init__.py
cmem/cmempy/dp/shacl/validation.py
cmem/cmempy/dp/titles/__init__.py
cmem/cmempy/dp/workspace/__init__.py
cmem/cmempy/health/__init__.py
cmem/cmempy/keycloak/client.py
cmem/cmempy/keycloak/group.py
cmem/cmempy/keycloak/user.py
cmem/cmempy/linking/__init__.py
cmem/cmempy/linking/linkingtask.py
cmem/cmempy/plugins/__init__.py
cmem/cmempy/plugins/marshalling.py
cmem/cmempy/queries/__init__.py
cmem/cmempy/transform/__init__.py
cmem/cmempy/transform/rules/__init__.py
cmem/cmempy/transform/rules/transformationrule.py
cmem/cmempy/transform/transformationtask.py
cmem/cmempy/vocabularies/__init__.py
cmem/cmempy/workflow/__init__.py
cmem/cmempy/workflow/workflow.py
cmem/cmempy/workflow/workflows.py
cmem/cmempy/workspace/__init__.py
cmem/cmempy/workspace/activities/__init__.py
cmem/cmempy/workspace/activities/projectactivities.py
cmem/cmempy/workspace/activities/projectactivity.py
cmem/cmempy/workspace/activities/taskactivities.py
cmem/cmempy/workspace/activities/taskactivity.py
cmem/cmempy/workspace/export_/__init__.py
cmem/cmempy/workspace/import_/__init__.py
cmem/cmempy/workspace/projects/__init__.py
cmem/cmempy/workspace/projects/datasets/__init__.py
cmem/cmempy/workspace/projects/datasets/dataset.py
cmem/cmempy/workspace/projects/export_.py
cmem/cmempy/workspace/projects/import_.py
cmem/cmempy/workspace/projects/project.py
cmem/cmempy/workspace/projects/resources/__init__.py
cmem/cmempy/workspace/projects/resources/resource.py
cmem/cmempy/workspace/projects/variables/__init__.py
cmem_cmempy-25.4.0.dist-info/METADATA
cmem_cmempy-25.4.0.dist-info/WHEEL
cmem_cmempy-25.4.0.dist-info/licenses/LICENSE
cmem_cmempy-25.4.0.dist-info/RECORD
